BookmarkParser/__init__.py
BookmarkParser/main.py
BookmarkParser/utils.py
BookmarkParser-1.0.0.dist-info/LICENSE.md
BookmarkParser-1.0.0.dist-info/METADATA
BookmarkParser-1.0.0.dist-info/WHEEL
BookmarkParser-1.0.0.dist-info/top_level.txt
BookmarkParser-1.0.0.dist-info/RECORD
