Metadata-Version: 2.1
Name: BookmarkParser
Version: 1.0.0
Summary: A Simple and clean way to explore Bookmarks Data.
Home-page: https://github.com/AidenEllis/BookmarkParser
Author: Aiden Ellis
Author-email: itsaidenellis@protonmail.com
License: MIT
Project-URL: Github, https://github.com/AidenEllis/BookmarkParser
Project-URL: Documentation, https://github.com/AidenEllis/BookmarkParser/blob/main/docs
Project-URL: Issue tracker, https://github.com/AidenEllis/BookmarkParser/issues
Keywords: BookmarkParser,Bookmarks,Chrome,Brave,Parser,Json,webbrowser
Platform: UNKNOWN
Classifier: Development Status :: 5 - Production/Stable
Classifier: Programming Language :: Python :: 3
Classifier: Operating System :: OS Independent
Classifier: License :: OSI Approved :: MIT License
Classifier: Natural Language :: English
Classifier: Intended Audience :: Developers
Classifier: Topic :: Software Development :: Libraries
Classifier: Topic :: Software Development :: Libraries :: Python Modules
Classifier: Topic :: Utilities
License-File: LICENSE.md
Requires-Dist: certifi
Requires-Dist: etils (==0.6.0)
Requires-Dist: ujson (==5.3.0)
Requires-Dist: wincertstore (==0.2)
